[
    {
        "title": "Master – Programmation / Management",
        "description": "Heriot Watt University – Edinburgh - Ecosse (Sept-Déc 2024 )",
        "image": "images/heriot.png"
    },
    {
        "title": "Cycle ingénieur en apprentissage filière Informatique et Applications ",
        "description": "ESIEE Paris – Université Gustave Eiffel (2022 - 2025)",
        "image": "images/esiee.png"
    },
    {
        "title": "Cycle préparatoire intégré",
        "description": "ESIEE Paris – Université Gustave Eiffel (2020 - 2022)",
        "image": "images/esiee.png"
    },
    {
        "title": "Baccalauréat S",
        "description": "Lycée Vauvenargues (Aix-en-Provence) – SI option ISN mention Assez Bien (2020)",
        "image": "images/bac.png"
    }
]
